falcon_swagger_ui/__init__.py
falcon_swagger_ui/resources.py
falcon_swagger_ui/dist/favicon-16x16.png
falcon_swagger_ui/dist/favicon-32x32.png
falcon_swagger_ui/dist/index.html
falcon_swagger_ui/dist/oauth2-redirect.html
falcon_swagger_ui/dist/swagger-ui-bundle.js
falcon_swagger_ui/dist/swagger-ui-bundle.js.map
falcon_swagger_ui/dist/swagger-ui-es-bundle-core.js
falcon_swagger_ui/dist/swagger-ui-es-bundle-core.js.map
falcon_swagger_ui/dist/swagger-ui-es-bundle.js
falcon_swagger_ui/dist/swagger-ui-es-bundle.js.map
falcon_swagger_ui/dist/swagger-ui-standalone-preset.js
falcon_swagger_ui/dist/swagger-ui-standalone-preset.js.map
falcon_swagger_ui/dist/swagger-ui.css
falcon_swagger_ui/dist/swagger-ui.css.map
falcon_swagger_ui/dist/swagger-ui.js
falcon_swagger_ui/dist/swagger-ui.js.map
falcon_swagger_ui/templates/index.html
falcon_swagger_ui-1.2.2.dist-info/LICENSE
falcon_swagger_ui-1.2.2.dist-info/METADATA
falcon_swagger_ui-1.2.2.dist-info/WHEEL
falcon_swagger_ui-1.2.2.dist-info/top_level.txt
falcon_swagger_ui-1.2.2.dist-info/RECORD
