Metadata-Version: 2.1
Name: falcon-swagger-ui
Version: 1.2.2
Summary: Swagger UI Application for Falcon
Home-page: https://github.com/rdidyk/falcon-swagger-ui
Author: Ruslan Didyk
Author-email: rdidyk@tmgtop.com
License: MIT
Download-URL: https://github.com/rdidyk/falcon-swagger-ui/archive/1.2.2.tar.gz
Keywords: falcon swagger
Platform: UNKNOWN
Classifier: Intended Audience :: Developers
Classifier: License :: OSI Approved :: MIT License
Classifier: Programming Language :: Python :: 3
Classifier: Programming Language :: Python :: 3.5
Classifier: Programming Language :: Python :: 3.6
Classifier: Programming Language :: Python :: 3.7
Classifier: Programming Language :: Python :: 3.8
Requires-Dist: falcon
Requires-Dist: Jinja2
